Metadata-Version: 1.1
Name: efaqa-corpus-raw
Version: 1.0.3
Summary: 心理咨询问答原始语料库（以下也称为“本数据集”，“本语料库”）是为应用人工智能技术于心理咨询领域制作的高品质语料，语料是爬取心理咨询领域公开的网站的数据，经过整理和脱敏制作而成。消息总文本字符数四千四百多万。
Home-page: https://github.com/chatopera/efaqa-corpus-raw
Author: Hai Liang Wang
Author-email: hain@chatopera.com
License: Chunsong Public License, version 1.0
Keywords: corpus,machine-learning,NLU,NLP,chatbot
Platform: UNKNOWN
Classifier: Intended Audience :: Developers
Classifier: Operating System :: OS Independent
Classifier: Natural Language :: Chinese (Simplified)
Classifier: Natural Language :: Chinese (Traditional)
Classifier: Programming Language :: Python
Classifier: Programming Language :: Python :: 3
Classifier: Programming Language :: Python :: 3.5
Classifier: Programming Language :: Python :: 3.6
Classifier: Programming Language :: Python :: 3.7
Classifier: Topic :: Text Processing
Classifier: Topic :: Text Processing :: Indexing
Classifier: Topic :: Text Processing :: Linguistic
